nancorrmp/__init__.py
nancorrmp/nancorrmp.py
test/__init__.py
test/test_benchmark_nancorrmp.py
test/test_nancorrmp.py
nancorrmp-0.23.dist-info/LICENSE.txt
nancorrmp-0.23.dist-info/METADATA
nancorrmp-0.23.dist-info/WHEEL
nancorrmp-0.23.dist-info/top_level.txt
nancorrmp-0.23.dist-info/RECORD
